{"runners":[{"id":"kusa.dynastyscans","name":"Dynasty Scans","thumbnail":"dynasty.png","version":0.6,"website":"https://dynasty-scans.com","supportedLanguages":["EN_US"],"rating":1,"path":"DynastyScans","environment":"source","hash":"18a8469a0853be2de12ff63711301f55ccf0cce0963d23726fa4101bf1ec03eb"},{"id":"kusa.mangapark","name":"MangaPark","version":0.2,"website":"https://mangapark.io","thumbnail":"mangapark.png","supportedLanguages":["EN_US"],"minSupportedAppVersion":"5.0","rating":1,"path":"MangaPark","environment":"source","hash":"f297d2724f5059a90288d80e8efd6fb2dadfa917a6191ce9b5af80ee5ce9a611"},{"id":"kusa.omegascans","name":"OmegaScans","thumbnail":"omega.png","version":1.2,"website":"https://omegascans.org","supportedLanguages":["EN_US"],"rating":2,"path":"OmegaScans","environment":"source","hash":"9e4c99ccb5ce0f54b62132f5075b66a261b50c6d6d83236c83cc83135161e3bd"},{"id":"kusa.readcomicsonline","name":"ReadComicsOnline.ru","version":0.1,"website":"https://readcomicsonline.ru","thumbnail":"readcomicsonline.png","supportedLanguages":["EN_US"],"minSupportedAppVersion":"5.0","rating":1,"path":"ReadComicsOnline","environment":"source","hash":"7309aa5a581216056bc6206a5d732af5894dbe62cda0e7a35c61a4f7753a1507"},{"id":"kusa.anilist","name":"Anilist","version":1.5,"website":"https://anilist.co","thumbnail":"anilist.png","path":"anilist","environment":"tracker","hash":"3b8c89374c9e24011aa92c1b9098d7c7d1af15d6405fa2c66f71a17920d68fb7"},{"id":"kusa.bato","name":"Bato","version":0.7,"website":"https://bato.to","supportedLanguages":["en","ar","bg","zh","cs","da","nl","fil","fi","fr","de","el","he","hi","hu","id","it","ja","ko","ms","pl","pt","pt_br","ro","ru","es","es_419","sv","th","tr","uk","vi","af","sq","am","hy","az","be","bn","bs","my","km","ca","ceb","zh_hk","zh_tw","hr","en_us","eo","et","fo","ka","gn","gu","ht","ha","is","ig","ga","jv","kn","kk","ku","ky","lo","lv","lt","lb","mk","mg","ml","mt","mi","mr","mo","mn","ne","no","ny","ps","fa","rm","sm","sr","sh","st","sn","sd","si","sk","sl","so","sw","tg","ta","ti","to","tk","ur","uz","yo","zu","_t"],"thumbnail":"bato.png","minSupportedAppVersion":"5.0","rating":1,"path":"bato","environment":"source","hash":"5fc5bcb4dbfee7a8c529153dc291720d79f4f33b36c404bd1090483fb21132cb"},{"id":"kusa.hiperdex","name":"Hiperdex","thumbnail":"hiperdex.png","version":0.3,"rating":2,"website":"https://hiperdex.com","supportedLanguages":["en"],"path":"hiperdex","environment":"source","hash":"5cfe1ffc555bcba81263a2382951a186203d011d54ae8ec34ddf66e8ebb34ced"},{"id":"kusa.mangago","name":"Mangago","thumbnail":"mangago.png","version":0.2,"website":"https://www.mangago.me","supportedLanguages":["EN_US"],"rating":1,"path":"mangago","environment":"source","hash":"c76c6002dc0b8624ac4213954f5ca60c097c9cf612f15a64d3e4f4b1c0708ee4"},{"id":"net.nhentai","name":"nHentai","version":0.5,"website":"https://nhentai.net","supportedLanguages":["EN_GB","JA","ZH"],"thumbnail":"nhentai.png","rating":2,"path":"nhentai","environment":"source","hash":"ce06ab3822d8dfcc1f4b93fc8e8507338204acecd9db8ffc9adeaf408baab1e5"},{"id":"kusa.toonily","name":"Toonily","thumbnail":"toonily.png","version":1.7,"website":"https://toonily.com","supportedLanguages":["EN_US"],"rating":1,"minSupportedAppVersion":"5.0","path":"toonily","environment":"source","hash":"823a0c8b3ff9deaf08c87b0bfee1feb8a88dd0463122fa127706f2428f187280"}],"listName":"Kusahime's Sources"}