{"runners":[{"id":"kusa.mangapark","name":"MangaPark","version":0.1,"website":"https://mangapark.io","thumbnail":"mangapark.png","supportedLanguages":["EN_US"],"minSupportedAppVersion":"5.0","rating":1,"path":"MangaPark","environment":"source","hash":"dfccc99f13d4ba7a1e838ec6dda0ea8e5aa27ab5a70494950f114bbb37d4462c"},{"id":"kusa.omegascans","name":"OmegaScans","thumbnail":"omega.png","version":1.2,"website":"https://omegascans.org","supportedLanguages":["EN_US"],"rating":2,"path":"OmegaScans","environment":"source","hash":"cd356b362cf99b68dbc8932e412eaea62e619ec1681a0ef6d9087e035a1d652f"},{"id":"li.readcomiconline","name":"ReadComicOnline","thumbnail":"readcomiconline.png","website":"https://readcomiconline.li","version":0.2,"supportedLanguages":["EN_US"],"rating":0,"path":"ReadComicOnline","environment":"source","hash":"b1385303daf2f03a08d12f9fdd208a9cb79a90d4227a3be540f7d8c0b98ef40c"},{"id":"kusa.anilist","name":"Anilist","version":1.5,"website":"https://anilist.co","thumbnail":"anilist.png","path":"anilist","environment":"tracker","hash":"8e242ef22be94e7e06a2244be3db78c65ab30b7e9f5b70f62544d5f6976250e1"},{"id":"kusa.bato","name":"Bato","version":0.7,"website":"https://bato.to","supportedLanguages":["en","ar","bg","zh","cs","da","nl","fil","fi","fr","de","el","he","hi","hu","id","it","ja","ko","ms","pl","pt","pt_br","ro","ru","es","es_419","sv","th","tr","uk","vi","af","sq","am","hy","az","be","bn","bs","my","km","ca","ceb","zh_hk","zh_tw","hr","en_us","eo","et","fo","ka","gn","gu","ht","ha","is","ig","ga","jv","kn","kk","ku","ky","lo","lv","lt","lb","mk","mg","ml","mt","mi","mr","mo","mn","ne","no","ny","ps","fa","rm","sm","sr","sh","st","sn","sd","si","sk","sl","so","sw","tg","ta","ti","to","tk","ur","uz","yo","zu","_t"],"thumbnail":"bato.png","minSupportedAppVersion":"5.0","rating":1,"path":"bato","environment":"source","hash":"b8180a9e667a143300d009492f9a4797200b2f1e2d86f0e0a347c5a91ee925e2"},{"id":"kusa.hiperdex","name":"Hiperdex","thumbnail":"hiperdex.png","version":0.3,"rating":2,"website":"https://hiperdex.com","supportedLanguages":["en"],"path":"hiperdex","environment":"source","hash":"4f89d62f3e053073215cbf5ab57331aef1772fcfc320eae10768118b9c6f1adb"},{"id":"kusa.mangago","name":"Mangago","thumbnail":"mangago.png","version":0.2,"website":"https://www.mangago.me","supportedLanguages":["EN_US"],"rating":1,"path":"mangago","environment":"source","hash":"3990ac6553dc7d914f25ffa5a0c73ad3fb38c4f1fa05cb5b832acb8f95b417c7"},{"id":"net.nhentai","name":"nHentai","version":0.5,"website":"https://nhentai.net","supportedLanguages":["EN_GB","JA","ZH"],"thumbnail":"nhentai.png","rating":2,"path":"nhentai","environment":"source","hash":"addf6e72b7bb40dd9c149e8e01205b7ccb99f2cf41e4f0387641c0e7249532e8"},{"id":"kusa.toonily","name":"Toonily","thumbnail":"toonily.png","version":1.7,"website":"https://toonily.com","supportedLanguages":["EN_US"],"rating":1,"minSupportedAppVersion":"5.0","path":"toonily","environment":"source","hash":"a3b70e397ea62055f3b3c998723b7a4fb99e707a5abae3f6b56c68d5e0c44ba1"}],"listName":"Kusahime's Sources"}